FullStackPythonZhongwenban/README.md
FullStackPythonZhongwenban/__init__.py
FullStackPythonZhongwenban/__main__.py
FullStackPythonZhongwenban/file.epub
FullStackPythonZhongwenban/index.html
FullStackPythonZhongwenban/css/__init__.py
FullStackPythonZhongwenban/css/annotations.css
FullStackPythonZhongwenban/css/main.css
FullStackPythonZhongwenban/css/normalize.css
FullStackPythonZhongwenban/css/popup.css
FullStackPythonZhongwenban/font/__init__.py
FullStackPythonZhongwenban/font/fontello.eot
FullStackPythonZhongwenban/font/fontello.svg
FullStackPythonZhongwenban/font/fontello.ttf
FullStackPythonZhongwenban/font/fontello.woff
FullStackPythonZhongwenban/img/__init__.py
FullStackPythonZhongwenban/img/annotator-glyph-sprite.png
FullStackPythonZhongwenban/img/annotator-icon-sprite.png
FullStackPythonZhongwenban/img/apple-touch-icon.png
FullStackPythonZhongwenban/img/cancelfullscreen.png
FullStackPythonZhongwenban/img/close.png
FullStackPythonZhongwenban/img/fullscreen.png
FullStackPythonZhongwenban/img/loader.gif
FullStackPythonZhongwenban/img/menu-icon.png
FullStackPythonZhongwenban/img/save.png
FullStackPythonZhongwenban/img/saved.png
FullStackPythonZhongwenban/img/settings-s.png
FullStackPythonZhongwenban/img/settings.png
FullStackPythonZhongwenban/img/star.png
FullStackPythonZhongwenban/js/__init__.py
FullStackPythonZhongwenban/js/epub.js
FullStackPythonZhongwenban/js/epub.min.js
FullStackPythonZhongwenban/js/epub.min.map
FullStackPythonZhongwenban/js/hooks.min.js
FullStackPythonZhongwenban/js/hooks.min.map
FullStackPythonZhongwenban/js/reader.js
FullStackPythonZhongwenban/js/reader.js.map
FullStackPythonZhongwenban/js/reader.min.js
FullStackPythonZhongwenban/js/reader.min.map
FullStackPythonZhongwenban/js/hooks/__init__.py
FullStackPythonZhongwenban/js/hooks/extensions/__init__.py
FullStackPythonZhongwenban/js/hooks/extensions/highlight.js
FullStackPythonZhongwenban/js/libs/__init__.py
FullStackPythonZhongwenban/js/libs/jquery.min.js
full_stack_python_zhongwenban-2024.3.5.0.dist-info/METADATA
full_stack_python_zhongwenban-2024.3.5.0.dist-info/WHEEL
full_stack_python_zhongwenban-2024.3.5.0.dist-info/entry_points.txt
full_stack_python_zhongwenban-2024.3.5.0.dist-info/top_level.txt
full_stack_python_zhongwenban-2024.3.5.0.dist-info/RECORD
